edat_ingestao_utils/__init__.py
edat_ingestao_utils/database.py
edat_ingestao_utils/postgresql.py
edat_ingestao_utils/s3_detic.py
edat_ingestao_utils/textual.py
edat_ingestao_utils-0.0.11.dist-info/METADATA
edat_ingestao_utils-0.0.11.dist-info/WHEEL
edat_ingestao_utils-0.0.11.dist-info/top_level.txt
edat_ingestao_utils-0.0.11.dist-info/RECORD
