Metadata-Version: 2.1
Name: edat-ingestao-utils
Version: 0.0.11
Summary: Biblioteca de Apoio a Ingestão de Dados no EDAT
Home-page: UNKNOWN
Author: Escritório de Dados
Author-email: dados@unicamp.br
License: MIT
Platform: UNKNOWN
Classifier: Intended Audience :: Developers
Classifier: License :: OSI Approved :: MIT License
Classifier: Programming Language :: Python
Classifier: Operating System :: OS Independent
Requires-Python: >=3.6
Requires-Dist: psycopg2 >=2.8.6
Requires-Dist: SQLAlchemy >=1.3.15
Requires-Dist: pandas >=0.24.2
Requires-Dist: pgcopy >=1.4.1
Requires-Dist: jellyfish >=0.8.2
Requires-Dist: boto3 ==1.33.13
